validio_sdk/__init__.py
validio_sdk/_api/__init__.py
validio_sdk/_api/api.py
validio_sdk/client/__init__.py
validio_sdk/client/client.py
validio_sdk/code/__init__.py
validio_sdk/code/_import.py
validio_sdk/code/_progress.py
validio_sdk/code/apply.py
validio_sdk/code/plan.py
validio_sdk/code/scaffold.py
validio_sdk/code/settings.py
validio_sdk/config.py
validio_sdk/dbt.py
validio_sdk/exception.py
validio_sdk/metadata.py
validio_sdk/py.typed
validio_sdk/resource/__init__.py
validio_sdk/resource/_diff.py
validio_sdk/resource/_diff_util.py
validio_sdk/resource/_diffable.py
validio_sdk/resource/_errors.py
validio_sdk/resource/_resource.py
validio_sdk/resource/_resource_graph.py
validio_sdk/resource/_serde.py
validio_sdk/resource/_server_resources.py
validio_sdk/resource/_update_namespace.py
validio_sdk/resource/_util.py
validio_sdk/resource/channels.py
validio_sdk/resource/credentials.py
validio_sdk/resource/enums.py
validio_sdk/resource/filters.py
validio_sdk/resource/notification_rules.py
validio_sdk/resource/replacement.py
validio_sdk/resource/segmentations.py
validio_sdk/resource/sources.py
validio_sdk/resource/tags.py
validio_sdk/resource/tests/__init__.py
validio_sdk/resource/tests/assets/example_manifest.json
validio_sdk/resource/tests/assets/expected_trimmed_manifest.json
validio_sdk/resource/tests/test__dbt.py
validio_sdk/resource/tests/test__diff.py
validio_sdk/resource/tests/test__plan.py
validio_sdk/resource/tests/test__resource.py
validio_sdk/resource/tests/test__sql_validation.py
validio_sdk/resource/tests/test_import.py
validio_sdk/resource/thresholds.py
validio_sdk/resource/validators.py
validio_sdk/resource/windows.py
validio_sdk/scalars.py
validio_sdk/util.py
validio_sdk-7.3.1.dist-info/LICENSE
validio_sdk-7.3.1.dist-info/METADATA
validio_sdk-7.3.1.dist-info/WHEEL
validio_sdk-7.3.1.dist-info/entry_points.txt
validio_sdk-7.3.1.dist-info/RECORD
