Metadata-Version: 2.1
Name: validio-sdk
Version: 7.3.1
Summary: SDK to interact with the Validio platform
Home-page: https://validio.io/
License: Apache-2.0
Author: Validio
Author-email: support@validio.io
Requires-Python: >=3.10,<4.0
Classifier: License :: OSI Approved :: Apache Software License
Classifier: Programming Language :: Python :: 3
Classifier: Programming Language :: Python :: 3.10
Classifier: Programming Language :: Python :: 3.11
Requires-Dist: camel-converter (>=3.0.0,<4.0.0)
Requires-Dist: gql[all] (>=3.5.0,<4.0.0)
Requires-Dist: platformdirs (>=3.5.0,<4.0.0)
Requires-Dist: rich (==13.9.4)
Project-URL: Documentation, https://dev.validio.io/sdk-docs
